README
setup.cfg
setup.py
django_localflavor_sl.egg-info/PKG-INFO
django_localflavor_sl.egg-info/SOURCES.txt
django_localflavor_sl.egg-info/dependency_links.txt
django_localflavor_sl.egg-info/not-zip-safe
django_localflavor_sl.egg-info/requires.txt
django_localflavor_sl.egg-info/top_level.txt
localflavor/__init__.py
localflavor/sl/__init__.py
localflavor/sl/forms.py
localflavor/sl/sl_postalcodes.py
localflavor/sl/tests.py