Metadata-Version: 1.0
Name: django-localflavor-sl
Version: 0.2
Summary: Slovenian Django localflavor
Home-page: UNKNOWN
Author: Domen Kozar
Author-email: Domen Kozar
License: UNKNOWN
Platform: UNKNOWN
